bashup/__init__.py
bashup/__main__.py
bashup/parse.py
bashup/compile/__init__.py
bashup/compile/bash.py
bashup/compile/elements/__init__.py
bashup/compile/elements/fn.py
bashup-2.0.2.dist-info/top_level.txt
bashup-2.0.2.dist-info/entry_points.txt
bashup-2.0.2.dist-info/METADATA
bashup-2.0.2.dist-info/DESCRIPTION.rst
bashup-2.0.2.dist-info/metadata.json
bashup-2.0.2.dist-info/WHEEL
bashup-2.0.2.dist-info/RECORD
