Metadata-Version: 2.0
Name: bashup
Version: 2.0.2
Summary: A (toy) language that compiles to bash.
Home-page: https://github.com/themattrix/bashup
Author: Matthew Tardiff
Author-email: mattrix@gmail.com
License: MIT
Platform: UNKNOWN
Classifier: License :: OSI Approved :: MIT License
Classifier: Programming Language :: Python :: 2
Classifier: Programming Language :: Python :: 2.6
Classifier: Programming Language :: Python :: 2.7
Classifier: Programming Language :: Python :: 3
Classifier: Programming Language :: Python :: 3.3
Classifier: Programming Language :: Python :: 3.4
Classifier: Programming Language :: Python :: 3.5
Classifier: Programming Language :: Python :: Implementation :: CPython
Classifier: Programming Language :: Python :: Implementation :: PyPy
Requires-Dist: docopt
Requires-Dist: Jinja2
Requires-Dist: pyparsing
Requires-Dist: temporary (>=3,<4)
